prompt_engineering/__init__.py
prompt_engineering/decorators.py
prompt_engineering/prompts.py
prompt_engineering/utils.py
prompt_engineering-0.0.6.dist-info/METADATA
prompt_engineering-0.0.6.dist-info/WHEEL
prompt_engineering-0.0.6.dist-info/top_level.txt
prompt_engineering-0.0.6.dist-info/RECORD
